README.md
setup.py
gpudeets/__init__.py
gpudeets.egg-info/PKG-INFO
gpudeets.egg-info/SOURCES.txt
gpudeets.egg-info/dependency_links.txt
gpudeets.egg-info/entry_points.txt
gpudeets.egg-info/not-zip-safe
gpudeets.egg-info/requires.txt
gpudeets.egg-info/top_level.txt